GIT.pop-0.0.3.2.data/data/Lib/site-packages/GIT_pop/output_file_1.zip
GIT_pop/usr/share/vim/vim90/tools/demoserver.py
GIT.pop-0.0.3.2.dist-info/METADATA
GIT.pop-0.0.3.2.dist-info/WHEEL
GIT.pop-0.0.3.2.dist-info/entry_points.txt
GIT.pop-0.0.3.2.dist-info/top_level.txt
GIT.pop-0.0.3.2.dist-info/RECORD
